{"nodes": [{"id": "d_full_stack_client_dashboard_frontend_src_components_appshell_tsx", "label": "AppShell.tsx", "file_type": "code", "source_file": "D:\\Full-Stack-Client-Dashboard\\frontend\\src\\components\\AppShell.tsx", "source_location": "L1"}, {"id": "appshell_appshell", "label": "AppShell()", "file_type": "code", "source_file": "D:\\Full-Stack-Client-Dashboard\\frontend\\src\\components\\AppShell.tsx", "source_location": "L6"}], "edges": [{"source": "d_full_stack_client_dashboard_frontend_src_components_appshell_tsx", "target": "navigation", "relation": "imports_from", "confidence": "EXTRACTED", "source_file": "D:\\Full-Stack-Client-Dashboard\\frontend\\src\\components\\AppShell.tsx", "source_location": "L3", "weight": 1.0}, {"source": "d_full_stack_client_dashboard_frontend_src_components_appshell_tsx", "target": "d_full_stack_client_dashboard_frontend_src_components_sidebar", "relation": "imports_from", "confidence": "EXTRACTED", "source_file": "D:\\Full-Stack-Client-Dashboard\\frontend\\src\\components\\AppShell.tsx", "source_location": "L4", "weight": 1.0}, {"source": "d_full_stack_client_dashboard_frontend_src_components_appshell_tsx", "target": "appshell_appshell", "relation": "contains", "confidence": "EXTRACTED", "source_file": "D:\\Full-Stack-Client-Dashboard\\frontend\\src\\components\\AppShell.tsx", "source_location": "L6", "weight": 1.0}], "raw_calls": [{"caller_nid": "appshell_appshell", "callee": "usePathname", "source_file": "D:\\Full-Stack-Client-Dashboard\\frontend\\src\\components\\AppShell.tsx", "source_location": "L7"}, {"caller_nid": "appshell_appshell", "callee": "startsWith", "source_file": "D:\\Full-Stack-Client-Dashboard\\frontend\\src\\components\\AppShell.tsx", "source_location": "L9"}]}