{"nodes": [{"id": "d_full_stack_client_dashboard_backend_app_core_config_py", "label": "config.py", "file_type": "code", "source_file": "D:\\Full-Stack-Client-Dashboard\\backend\\app\\core\\config.py", "source_location": "L1"}, {"id": "config_settings", "label": "Settings", "file_type": "code", "source_file": "D:\\Full-Stack-Client-Dashboard\\backend\\app\\core\\config.py", "source_location": "L16"}, {"id": "basesettings", "label": "BaseSettings", "file_type": "code", "source_file": "", "source_location": ""}, {"id": "config_config", "label": "Config", "file_type": "code", "source_file": "D:\\Full-Stack-Client-Dashboard\\backend\\app\\core\\config.py", "source_location": "L61"}, {"id": "config_rationale_1", "label": "Application configuration \u2014 loaded from .env via python-dotenv. Extend this as", "file_type": "rationale", "source_file": "D:\\Full-Stack-Client-Dashboard\\backend\\app\\core\\config.py", "source_location": "L1"}], "edges": [{"source": "d_full_stack_client_dashboard_backend_app_core_config_py", "target": "os", "relation": "imports", "confidence": "EXTRACTED", "source_file": "D:\\Full-Stack-Client-Dashboard\\backend\\app\\core\\config.py", "source_location": "L6", "weight": 1.0}, {"source": "d_full_stack_client_dashboard_backend_app_core_config_py", "target": "pydantic_settings", "relation": "imports_from", "confidence": "EXTRACTED", "source_file": "D:\\Full-Stack-Client-Dashboard\\backend\\app\\core\\config.py", "source_location": "L7", "weight": 1.0}, {"source": "d_full_stack_client_dashboard_backend_app_core_config_py", "target": "config_settings", "relation": "contains", "confidence": "EXTRACTED", "source_file": "D:\\Full-Stack-Client-Dashboard\\backend\\app\\core\\config.py", "source_location": "L16", "weight": 1.0}, {"source": "config_settings", "target": "basesettings", "relation": "inherits", "confidence": "EXTRACTED", "source_file": "D:\\Full-Stack-Client-Dashboard\\backend\\app\\core\\config.py", "source_location": "L16", "weight": 1.0}, {"source": "d_full_stack_client_dashboard_backend_app_core_config_py", "target": "config_config", "relation": "contains", "confidence": "EXTRACTED", "source_file": "D:\\Full-Stack-Client-Dashboard\\backend\\app\\core\\config.py", "source_location": "L61", "weight": 1.0}, {"source": "config_rationale_1", "target": "d_full_stack_client_dashboard_backend_app_core_config_py", "relation": "rationale_for", "confidence": "EXTRACTED", "source_file": "D:\\Full-Stack-Client-Dashboard\\backend\\app\\core\\config.py", "source_location": "L1", "weight": 1.0}], "raw_calls": []}